README
setup.py
data_tools/__init__.py
data_tools/configurable.py
data_tools/data_tools_tests.py
data_tools/safe_eval.py
data_tools.egg-info/PKG-INFO
data_tools.egg-info/SOURCES.txt
data_tools.egg-info/dependency_links.txt
data_tools.egg-info/top_level.txt