Metadata-Version: 1.0
Name: data-tools
Version: 0.2
Summary: Tools for data engineers
Home-page: https://github.com/coxg/data_tools
Author: Gaven Cox
Author-email: gavencox@gmail.com
License: MIT
Platform: UNKNOWN
